sr_flipflop/srflipflop.v
module srflipflop (
    input clk,
    input rst_n,      // Active-low synchronous reset
    input s, r,
    output reg q,
    output q_bar
);

    always @(posedge clk) begin
        if (!rst_n) begin
            q <= 1'b0;
        end else begin
            case ({s, r})
                2'b00: q <= q;       // Hold state
                2'b01: q <= 1'b0;    // Reset
                2'b10: q <= 1'b1;    // Set
                2'b11: q <= 1'bx;    // Invalid state
                default: q <= q;
            endcase
        end
    end

    assign q_bar = ~q;

endmodule

sr_flipflop/srflipflop_tb.v
module srflipflop_tb;
    
    reg clk;
    reg s;
    reg r;
    wire q;
    wire q_bar;

    srflipflop dut (
        .clk(clk),
        .s(s),
        .r(r),
        .q(q),
        .q_bar(q_bar)
    );

    initial begin
        clk = 0;
        forever #25 clk = ~clk;
    end

   
    initial begin
    $dumpfile("wave.vcd");
    $dumpvars(0, srflipflop_tb);
        s = 0;
        r = 0;
        
       
        #50; 
        
        s = 0; r = 1;
        #50;
        
       
        s = 1; r = 0;
        #50;
        
   
        s = 1; r = 1;
        #50;
        
  
        s = 0; r = 0;
        #50;
   
        $finish;
    end

  
    initial begin
        $monitor("Time=%0t | S=%b R=%b | Q=%b Q_bar=%b", $time, s, r, q, q_bar);
    end
endmodule

sr_flipflop/wave.vcd
$date
	Thu Sep 10 01:05:34 2026
$end
$version
	Icarus Verilog
$end
$timescale
	1s
$end
$scope module srflipflop_tb $end
$var wire 1 ! q_bar $end
$var wire 1 " q $end
$var reg 1 # clk $end
$var reg 1 $ r $end
$var reg 1 % s $end
$scope module dut $end
$var wire 1 # clk $end
$var wire 1 ! q_bar $end
$var wire 1 $ r $end
$var wire 1 & rst_n $end
$var wire 1 % s $end
$var reg 1 " q $end
$upscope $end
$upscope $end
$enddefinitions $end
$comment Show the parameter values. $end
$dumpall
$end
#0
$dumpvars
z&
0%
0$
0#
x"
x!
$end
#25
1#
#50
0#
1$
#75
1!
0"
1#
#100
0#
0$
1%
#125
0!
1"
1#
#150
0#
1$
#175
x!
x"
1#
#200
0#
0$
0%
