3 : 8 decoder/decoder3_8.v
module decoder_3to8_beh (
 input En,A,B,C,
 output reg [7:0] Y
);
 always @(*) begin
 // If Enable is 0, all outputs are 0
 if (En == 1'b0) begin
 Y = 8'b0000_0000;
 end
 // If Enable is 1, decode the inputs
 else begin
 case ({A, B, C}) // Concatenate A, B, and C into a 3-bit vector
 3'b000: Y = 8'b0000_0001;
 3'b001: Y = 8'b0000_0010;
 3'b010: Y = 8'b0000_0100;
 3'b011: Y = 8'b0000_1000;
 3'b100: Y = 8'b0001_0000;
 3'b101: Y = 8'b0010_0000;
 3'b110: Y = 8'b0100_0000;
 3'b111: Y = 8'b1000_0000;
 default: Y = 8'b0000_0000; // Good practice to prevent latches
 endcase
 end
 end
endmodule

3 : 8 decoder/decoder3_8_tb.v
module decoder_3to8_beh_tb;
 reg En, A, B, C;
 wire [7:0] Y;
 integer i; // Used as a counter for the 'for' loop
 decoder_3to8_beh dut (En, A, B, C,Y);
 initial begin
 $dumpfile("wave.vcd");
$dumpvars(0, decoder_3to8_beh_tb);
 // Print the headers and the values whenever they change
 $display("Time | En | A B C | Y");
 $display("--------------------------------");
 $monitor("%4t | %b | %b %b %b | %b", $time, En, A, B, C, Y);
 // --- Test 1: Decoder Disabled (En = 0) ---
 En = 0;
 A = 0; B = 0; C = 0; #10;
 // Even if inputs change, output should remain 00000000
 A = 1; B = 1; C = 1; #10;
 // --- Test 2: Decoder Enabled (En = 1) ---
 En = 1;
 // Loop from 0 to 7 (the 8 possible combinations)
 for (i = 0; i < 8; i = i + 1) begin
 // We can assign the integer 'i' directly to the concatenated inputs
 {A, B, C} = i;
 #10; // Wait 10 time units for the output to evaluate
 end
 end
endmodule

3 : 8 decoder/wave.vcd
$date
	Mon Sep 14 10:56:13 2026
$end
$version
	Icarus Verilog
$end
$timescale
	1s
$end
$scope module decoder_3to8_beh_tb $end
$var wire 8 ! Y [7:0] $end
$var reg 1 " A $end
$var reg 1 # B $end
$var reg 1 $ C $end
$var reg 1 % En $end
$var integer 32 & i [31:0] $end
$scope module dut $end
$var wire 1 " A $end
$var wire 1 # B $end
$var wire 1 $ C $end
$var wire 1 % En $end
$var reg 8 ' Y [7:0] $end
$upscope $end
$upscope $end
$enddefinitions $end
$comment Show the parameter values. $end
$dumpall
$end
#0
$dumpvars
b0 '
bx &
0%
0$
0#
0"
b0 !
$end
#10
1$
1#
1"
#20
b1 !
b1 '
0"
0#
0$
b0 &
1%
#30
b10 !
b10 '
1$
b1 &
#40
b100 !
b100 '
1#
0$
b10 &
#50
b1000 !
b1000 '
1$
b11 &
#60
b10000 !
b10000 '
1"
0#
0$
b100 &
#70
b100000 !
b100000 '
1$
b101 &
#80
b1000000 !
b1000000 '
1#
0$
b110 &
#90
b10000000 !
b10000000 '
1$
b111 &
#100
b1000 &
