jkflipflop/jkflipflop.v
module jkflipflop(
    input j,k,clk,
    output reg q,
    output qbar
);

always @(posedge clk) begin
    if(j==0 && k==0)
        q <= q;       // Hold
    else if(j==0 && k==1)
        q <= 0;       // Reset
    else if(j==1 && k==0)
        q <= 1;       // Set
    else
        q <= ~q;      // Toggle
end

assign qbar = ~q;

endmodule

jkflipflop/jkflipflop_tb.v
`timescale 1ns/1ps

module jkflipflop_tb;

reg j,k,clk;
wire q,qbar;

jkflipflop dut(.j(j), .k(k), .clk(clk), .q(q), .qbar(qbar));

initial begin
    $dumpfile("wave.vcd");
    $dumpvars(0, jkflipflop_tb);

    j = 0;
    k = 0;
    clk = 0;

    #10 j = 0; k = 1;
    #10 j = 1; k = 0;
    #10 j = 1; k = 1;
    #10 j = 1; k = 1;
    #10 j = 0; k = 0;

    #10 $finish;
end

always #5 clk = ~clk;

initial begin
    $monitor($time, " j=%b, k=%b, clk=%b, q=%b, qbar=%b",
             j, k, clk, q, qbar);
end

endmodule

jkflipflop/wave.vcd
$date
	Sun Sep  6 08:10:44 2026
$end
$version
	Icarus Verilog
$end
$timescale
	1ps
$end
$scope module jkflipflop_tb $end
$var wire 1 ! qbar $end
$var wire 1 " q $end
$var reg 1 # clk $end
$var reg 1 $ j $end
$var reg 1 % k $end
$scope module dut $end
$var wire 1 # clk $end
$var wire 1 $ j $end
$var wire 1 % k $end
$var wire 1 ! qbar $end
$var reg 1 " q $end
$upscope $end
$upscope $end
$enddefinitions $end
$comment Show the parameter values. $end
$dumpall
$end
#0
$dumpvars
0%
0$
0#
x"
x!
$end
#5000
1#
#10000
0#
1%
#15000
1!
0"
1#
#20000
0#
0%
1$
#25000
0!
1"
1#
#30000
0#
1%
#35000
1!
0"
1#
#40000
0#
#45000
0!
1"
1#
#50000
0#
0%
0$
