2:1 mux/mux2_1.v
module mux2_1(
    input s, input i0, input i1, output y
);
wire w1,w2,w3;
assign w1=~s;
assign w2=w1 & i0;
assign w3=s & i1;
assign y= w2 | w3;
endmodule

2:1 mux/mux2_1_tb.v
`timescale 1ns/1ps
module mux2_1_tb;
reg h1, h2, h3;
wire z;
mux2_1 dut(.s(h1), .i0(h2), .i1(h3), .y(z));
initial begin
$dumpfile("wave.vcd");
$dumpvars(0, mux2_1_tb);
#10 h1=0; h2=0; h3=0;
#10 h1=0; h2=0; h3=1;
#10 h1=0; h2=1; h3=0;
#10 h1=0; h2=1; h3=1;
#10 h1=1; h2=0; h3=0;
#10 h1=1; h2=0; h3=1;
#10 h1=1; h2=1; h3=0;
#10 h1=1; h2=1; h3=1;
#20 $finish;
end
initial begin 
$monitor ($time,"h1=%b, h2=%b, h3=%b,z=%b",h1, h2, h3, z);
end
endmodule

2:1 mux/wave.vcd
$date
	Thu Sep 10 04:31:58 2026
$end
$version
	Icarus Verilog
$end
$timescale
	1ps
$end
$scope module mux2_1_tb $end
$var wire 1 ! z $end
$var reg 1 " h1 $end
$var reg 1 # h2 $end
$var reg 1 $ h3 $end
$scope module dut $end
$var wire 1 # i0 $end
$var wire 1 $ i1 $end
$var wire 1 " s $end
$var wire 1 % w1 $end
$var wire 1 & w2 $end
$var wire 1 ' w3 $end
$var wire 1 ! y $end
$upscope $end
$upscope $end
$enddefinitions $end
$comment Show the parameter values. $end
$dumpall
$end
#0
$dumpvars
x'
x&
x%
x$
x#
x"
x!
$end
#10000
0!
0&
1%
0'
0$
0#
0"
#20000
1$
#30000
1!
1&
0$
1#
#40000
1$
#50000
0!
0&
0%
0$
0#
1"
#60000
1!
1'
1$
#70000
0!
0'
0$
1#
#80000
1!
1'
1$
