dlatch/dflipflop.v
module dflipflop(
  input d,clk,
  output q,qbar
);
wire dbar,a1,a2;
assign dbar=~d;

nand n1(a1,d,clk);
nand n2(a2,dbar,clk);
nand n3(q,a1,qbar);
nand n4(qbar,a2,q);
endmodule

dlatch/dflipflop_tb.v
`timescale 1ns/1ps
module dflipflop_tb;
reg d1,clk1;
wire q1,q2;
dflipflop dut (.d(d1), .clk(clk1), .q(q1), .qbar(q2));
initial begin
$dumpfile("wave.vcd");
$dumpvars(0, dflipflop_tb);

    d1 = 0;
    clk1 = 0;

    #10 clk1 = 1;
    #10 d1 = 1;
    #10 d1 = 0;
    #10 clk1 = 0;
    #10 d1 = 1;
    #10 d1 =0;
    #10 clk1 = 1;
#20 $finish;
end
initial begin 
$monitor ($time,"d1=%b, clk1=%b, q1=%b, q2=%b",d1, clk1, q1, q2);
end
endmodule

dlatch/wave.vcd
$date
	Fri Sep  4 01:49:30 2026
$end
$version
	Icarus Verilog
$end
$timescale
	1ps
$end
$scope module dflipflop_tb $end
$var wire 1 ! q2 $end
$var wire 1 " q1 $end
$var reg 1 # clk1 $end
$var reg 1 $ d1 $end
$scope module dut $end
$var wire 1 % a1 $end
$var wire 1 & a2 $end
$var wire 1 # clk $end
$var wire 1 $ d $end
$var wire 1 ' dbar $end
$var wire 1 " q $end
$var wire 1 ! qbar $end
$upscope $end
$upscope $end
$enddefinitions $end
$comment Show the parameter values. $end
$dumpall
$end
#0
$dumpvars
1'
1&
1%
0$
0#
x"
x!
$end
#10000
0"
1!
0&
1#
#20000
0!
1&
1"
0'
0%
1$
#30000
0"
1!
0&
1'
1%
0$
#40000
1&
0#
#50000
0'
1$
#60000
1'
0$
#70000
0&
1#
