4:1 mux/mux4_2.v
module mux4_2(
    input s0, input s1, input i0, input i1, input i2, input i3, output y
);
wire w1,w2,w3,w4,w5,w6;
assign w1=~s0;
assign w2=~s1;
assign w3=w1 & w2 & i0;
assign w4=w2 & s0 & i1;
assign w5=w1 & s1 & i2;
assign w6=s0 & s1 & i3;
assign y= w3 | w4 | w5 | w6;
endmodule

4:1 mux/mux4_2_tb.v
`timescale 1ns/1ps
module mux4_2_tb;
reg h1, h2, h3, h4, h5, h6;
wire z;
integer i;
mux4_2 dut(.s0(h1), .s1(h2), .i0(h3), .i1(h4), .i2(h5), .i3(h6), .y(z));
initial begin
$dumpfile("wave.vcd");
$dumpvars(0, mux4_2_tb);
  for (i = 0; i < 64; i = i + 1) begin
    #10 {h1, h2, h3, h4, h5, h6} = i[5:0];
end
#20 $finish;
end
initial begin 
$monitor ($time,"h1=%b, h2=%b, h3=%b,h4=%b, h5=%b, h6=%b ,z=%b",h1, h2, h3, h4, h5, h6, z);
end
endmodule

4:1 mux/wave.vcd
$date
	Thu Sep 10 05:07:15 2026
$end
$version
	Icarus Verilog
$end
$timescale
	1ps
$end
$scope module mux4_2_tb $end
$var wire 1 ! z $end
$var reg 1 " h1 $end
$var reg 1 # h2 $end
$var reg 1 $ h3 $end
$var reg 1 % h4 $end
$var reg 1 & h5 $end
$var reg 1 ' h6 $end
$var integer 32 ( i [31:0] $end
$scope module dut $end
$var wire 1 $ i0 $end
$var wire 1 % i1 $end
$var wire 1 & i2 $end
$var wire 1 ' i3 $end
$var wire 1 " s0 $end
$var wire 1 # s1 $end
$var wire 1 ) w1 $end
$var wire 1 * w2 $end
$var wire 1 + w3 $end
$var wire 1 , w4 $end
$var wire 1 - w5 $end
$var wire 1 . w6 $end
$var wire 1 ! y $end
$upscope $end
$upscope $end
$enddefinitions $end
$comment Show the parameter values. $end
$dumpall
$end
#0
$dumpvars
x.
x-
x,
x+
x*
x)
b0 (
x'
x&
x%
x$
x#
x"
x!
$end
#10000
0!
1)
1*
0+
0,
0-
0.
b1 (
0"
0#
0$
0%
0&
0'
#20000
b10 (
1'
#30000
b11 (
1&
0'
#40000
b100 (
1'
#50000
b101 (
1%
0&
0'
#60000
b110 (
1'
#70000
b111 (
1&
0'
#80000
b1000 (
1'
#90000
1!
1+
b1001 (
1$
0%
0&
0'
#100000
b1010 (
1'
#110000
b1011 (
1&
0'
#120000
b1100 (
1'
#130000
b1101 (
1%
0&
0'
#140000
b1110 (
1'
#150000
b1111 (
1&
0'
#160000
b10000 (
1'
#170000
0!
0*
0+
b10001 (
1#
0$
0%
0&
0'
#180000
b10010 (
1'
#190000
1!
1-
b10011 (
1&
0'
#200000
b10100 (
1'
#210000
0!
0-
b10101 (
1%
0&
0'
#220000
b10110 (
1'
#230000
1!
1-
b10111 (
1&
0'
#240000
b11000 (
1'
#250000
0!
0-
b11001 (
1$
0%
0&
0'
#260000
b11010 (
1'
#270000
1!
1-
b11011 (
1&
0'
#280000
b11100 (
1'
#290000
0!
0-
b11101 (
1%
0&
0'
#300000
b11110 (
1'
#310000
1!
1-
b11111 (
1&
0'
#320000
b100000 (
1'
#330000
0!
0)
1*
0-
b100001 (
1"
0#
0$
0%
0&
0'
#340000
b100010 (
1'
#350000
b100011 (
1&
0'
#360000
b100100 (
1'
#370000
1!
1,
b100101 (
1%
0&
0'
#380000
b100110 (
1'
#390000
b100111 (
1&
0'
#400000
b101000 (
1'
#410000
0!
0,
b101001 (
1$
0%
0&
0'
#420000
b101010 (
1'
#430000
b101011 (
1&
0'
#440000
b101100 (
1'
#450000
1!
1,
b101101 (
1%
0&
0'
#460000
b101110 (
1'
#470000
b101111 (
1&
0'
#480000
b110000 (
1'
#490000
0!
0*
0,
b110001 (
1#
0$
0%
0&
0'
#500000
1!
1.
b110010 (
1'
#510000
0!
0.
b110011 (
1&
0'
#520000
1!
1.
b110100 (
1'
#530000
0!
0.
b110101 (
1%
0&
0'
#540000
1!
1.
b110110 (
1'
#550000
0!
0.
b110111 (
1&
0'
#560000
1!
1.
b111000 (
1'
#570000
0!
0.
b111001 (
1$
0%
0&
0'
#580000
1!
1.
b111010 (
1'
#590000
0!
0.
b111011 (
1&
0'
#600000
1!
1.
b111100 (
1'
#610000
0!
0.
b111101 (
1%
0&
0'
#620000
1!
1.
b111110 (
1'
#630000
0!
0.
b111111 (
1&
0'
#640000
1!
1.
b1000000 (
1'
