8:3 encoder/Encoder8to3.v
module Encoder8to3(
input [7:0] I,
output [2:0] Y);
assign Y[0] = I[1]|I[3]|I[5]|I[7];
assign Y[1] = I[2]|I[3]|I[6]|I[7];
assign Y[2] = I[4]|I[5]|I[6]|I[7];
endmodule

8:3 encoder/Encoder8to3_tb.v
module Encoder8to3_tb;
reg [7:0] I;
wire [2:0] Y;
Encoder8to3 dut (I,Y);
initial begin
$dumpfile("wave.vcd");
$dumpvars(0, Encoder8to3_tb);
I = 8'b00000000; #10;
I = 8'b00000010; #10;
I = 8'b00000100; #10;
I = 8'b00001000; #10;
I = 8'b00010000; #10;
I = 8'b00100000; #10;
I = 8'b01000000; #10;
I = 8'b10000000; #10;
end
endmodule

8:3 encoder/wave.vcd
$date
	Wed Sep 23 17:01:09 2026
$end
$version
	Icarus Verilog
$end
$timescale
	1s
$end
$scope module Encoder8to3_tb $end
$var wire 3 ! Y [2:0] $end
$var reg 8 " I [7:0] $end
$scope module dut $end
$var wire 8 # I [7:0] $end
$var wire 3 $ Y [2:0] $end
$upscope $end
$upscope $end
$enddefinitions $end
$comment Show the parameter values. $end
$dumpall
$end
#0
$dumpvars
b0 $
b0 #
b0 "
b0 !
$end
#10
b1 !
b1 $
b10 "
b10 #
#20
b10 !
b10 $
b100 "
b100 #
#30
b11 !
b11 $
b1000 "
b1000 #
#40
b100 !
b100 $
b10000 "
b10000 #
#50
b101 !
b101 $
b100000 "
b100000 #
#60
b110 !
b110 $
b1000000 "
b1000000 #
#70
b111 !
b111 $
b10000000 "
b10000000 #
