8:1 mux/mux8_1.v
module mux8_1(
    input s0, input s1, input s2, input i0, input i1, input i2, input i3, input i4, input i5, input i6, input i7, output y
);
wire w1,w2,w3,w4,w5,w6,w7,w8,w9,w10,w11;
assign w1=~s0;
assign w2=~s1;
assign w3=~s2;
and a1(w4,  w1, w2, w3);
and a2(w5,  w1, w2, s2);
and a3(w6,  w1, s1, w3);
and a4(w7,  w1, s1, s2);
and a5(w8,  s0, w2, w3);
and a6(w9,  s0, w2, s2);
and a7(w10, s0, s1, w3);
and a8(w11, s0, s1, s2);
or  o1(y,w4,w5,w6,w7,w8,w9,w10,w11);
endmodule

8:1 mux/mux8_1_tb.v
`timescale 1ns/1ps
module mux8_1_tb;
reg h1, h2, h3, h4, h5, h6, h7, h8, h9, h10, h11;
wire z;
integer i;
mux8_1 dut(.s0(h1), .s1(h2), .s2(h3), .i0(h4), .i1(h5), .i2(h6), .i3(h7), .i4(h8), .i5(h9), .i6(h10), .i7(h11), .y(z));
initial begin
$dumpfile("wave.vcd");
$dumpvars(0, mux8_1_tb);
  for (i = 0; i < 2048; i = i + 1) begin
    #10 {h1, h2, h3, h4, h5, h6, h7, h8, h9, h10, h11} = i[10:0];
end
#20 $finish;
end
initial begin 
$monitor ($time,"h1=%b, h2=%b, h3=%b,h4=%b, h5=%b, h6=%b h7=%b, h8=%b, h9=%b,h10=%b, h11=%b ,z=%b",h1, h2, h3, h4, h5, h6, h7, h8, h9, h10, h11, z);
end
endmodule

8:1 mux/wave.vcd
$date
	Sun Sep 13 12:04:14 2026
$end
$version
	Icarus Verilog
$end
$timescale
	1ps
$end
$scope module mux8_1_tb $end
$var wire 1 ! z $end
$var reg 1 " h1 $end
$var reg 1 # h10 $end
$var reg 1 $ h11 $end
$var reg 1 % h2 $end
$var reg 1 & h3 $end
$var reg 1 ' h4 $end
$var reg 1 ( h5 $end
$var reg 1 ) h6 $end
$var reg 1 * h7 $end
$var reg 1 + h8 $end
$var reg 1 , h9 $end
$var integer 32 - i [31:0] $end
$scope module dut $end
$var wire 1 ' i0 $end
$var wire 1 ( i1 $end
$var wire 1 ) i2 $end
$var wire 1 * i3 $end
$var wire 1 + i4 $end
$var wire 1 , i5 $end
$var wire 1 # i6 $end
$var wire 1 $ i7 $end
$var wire 1 " s0 $end
$var wire 1 % s1 $end
$var wire 1 & s2 $end
$var wire 1 . w1 $end
$var wire 1 / w10 $end
$var wire 1 0 w11 $end
$var wire 1 1 w2 $end
$var wire 1 2 w3 $end
$var wire 1 3 w4 $end
$var wire 1 4 w5 $end
$var wire 1 5 w6 $end
$var wire 1 6 w7 $end
$var wire 1 7 w8 $end
$var wire 1 8 w9 $end
$var wire 1 ! y $end
$upscope $end
$upscope $end
$enddefinitions $end
$comment Show the parameter values. $end
$dumpall
$end
#0
$dumpvars
x8
x7
x6
x5
x4
x3
x2
x1
x0
x/
x.
b0 -
x,
x+
x*
x)
x(
x'
x&
x%
x$
x#
x"
x!
$end
#10000
1!
13
1.
07
11
05
0/
12
04
06
08
00
b1 -
0"
0%
0&
0'
0(
0)
0*
0+
0,
0#
0$
#20000
b10 -
1$
#30000
b11 -
1#
0$
#40000
b100 -
1$
#50000
b101 -
1,
0#
0$
#60000
b110 -
1$
#70000
b111 -
1#
0$
#80000
b1000 -
1$
#90000
b1001 -
1+
0,
0#
0$
#100000
b1010 -
1$
#110000
b1011 -
1#
0$
#120000
b1100 -
1$
#130000
b1101 -
1,
0#
0$
#140000
b1110 -
1$
#150000
b1111 -
1#
0$
#160000
b10000 -
1$
#170000
b10001 -
1*
0+
0,
0#
0$
#180000
b10010 -
1$
#190000
b10011 -
1#
0$
#200000
b10100 -
1$
#210000
b10101 -
1,
0#
0$
#220000
b10110 -
1$
#230000
b10111 -
1#
0$
#240000
b11000 -
1$
#250000
b11001 -
1+
0,
0#
0$
#260000
b11010 -
1$
#270000
b11011 -
1#
0$
#280000
b11100 -
1$
#290000
b11101 -
1,
0#
0$
#300000
b11110 -
1$
#310000
b11111 -
1#
0$
#320000
b100000 -
1$
#330000
b100001 -
1)
0*
0+
0,
0#
0$
#340000
b100010 -
1$
#350000
b100011 -
1#
0$
#360000
b100100 -
1$
#370000
b100101 -
1,
0#
0$
#380000
b100110 -
1$
#390000
b100111 -
1#
0$
#400000
b101000 -
1$
#410000
b101001 -
1+
0,
0#
0$
#420000
b101010 -
1$
#430000
b101011 -
1#
0$
#440000
b101100 -
1$
#450000
b101101 -
1,
0#
0$
#460000
b101110 -
1$
#470000
b101111 -
1#
0$
#480000
b110000 -
1$
#490000
b110001 -
1*
0+
0,
0#
0$
#500000
b110010 -
1$
#510000
b110011 -
1#
0$
#520000
b110100 -
1$
#530000
b110101 -
1,
0#
0$
#540000
b110110 -
1$
#550000
b110111 -
1#
0$
#560000
b111000 -
1$
#570000
b111001 -
1+
0,
0#
0$
#580000
b111010 -
1$
#590000
b111011 -
1#
0$
#600000
b111100 -
1$
#610000
b111101 -
1,
0#
0$
#620000
b111110 -
1$
#630000
b111111 -
1#
0$
#640000
b1000000 -
1$
#650000
b1000001 -
1(
0)
0*
0+
0,
0#
0$
#660000
b1000010 -
1$
#670000
b1000011 -
1#
0$
#680000
b1000100 -
1$
#690000
b1000101 -
1,
0#
0$
#700000
b1000110 -
1$
#710000
b1000111 -
1#
0$
#720000
b1001000 -
1$
#730000
b1001001 -
1+
0,
0#
0$
#740000
b1001010 -
1$
#750000
b1001011 -
1#
0$
#760000
b1001100 -
1$
#770000
b1001101 -
1,
0#
0$
#780000
b1001110 -
1$
#790000
b1001111 -
1#
0$
#800000
b1010000 -
1$
#810000
b1010001 -
1*
0+
0,
0#
0$
#820000
b1010010 -
1$
#830000
b1010011 -
1#
0$
#840000
b1010100 -
1$
#850000
b1010101 -
1,
0#
0$
#860000
b1010110 -
1$
#870000
b1010111 -
1#
0$
#880000
b1011000 -
1$
#890000
b1011001 -
1+
0,
0#
0$
#900000
b1011010 -
1$
#910000
b1011011 -
1#
0$
#920000
b1011100 -
1$
#930000
b1011101 -
1,
0#
0$
#940000
b1011110 -
1$
#950000
b1011111 -
1#
0$
#960000
b1100000 -
1$
#970000
b1100001 -
1)
0*
0+
0,
0#
0$
#980000
b1100010 -
1$
#990000
b1100011 -
1#
0$
#1000000
b1100100 -
1$
#1010000
b1100101 -
1,
0#
0$
#1020000
b1100110 -
1$
#1030000
b1100111 -
1#
0$
#1040000
b1101000 -
1$
#1050000
b1101001 -
1+
0,
0#
0$
#1060000
b1101010 -
1$
#1070000
b1101011 -
1#
0$
#1080000
b1101100 -
1$
#1090000
b1101101 -
1,
0#
0$
#1100000
b1101110 -
1$
#1110000
b1101111 -
1#
0$
#1120000
b1110000 -
1$
#1130000
b1110001 -
1*
0+
0,
0#
0$
#1140000
b1110010 -
1$
#1150000
b1110011 -
1#
0$
#1160000
b1110100 -
1$
#1170000
b1110101 -
1,
0#
0$
#1180000
b1110110 -
1$
#1190000
b1110111 -
1#
0$
#1200000
b1111000 -
1$
#1210000
b1111001 -
1+
0,
0#
0$
#1220000
b1111010 -
1$
#1230000
b1111011 -
1#
0$
#1240000
b1111100 -
1$
#1250000
b1111101 -
1,
0#
0$
#1260000
b1111110 -
1$
#1270000
b1111111 -
1#
0$
#1280000
b10000000 -
1$
#1290000
b10000001 -
1'
0(
0)
0*
0+
0,
0#
0$
#1300000
b10000010 -
1$
#1310000
b10000011 -
1#
0$
#1320000
b10000100 -
1$
#1330000
b10000101 -
1,
0#
0$
#1340000
b10000110 -
1$
#1350000
b10000111 -
1#
0$
#1360000
b10001000 -
1$
#1370000
b10001001 -
1+
0,
0#
0$
#1380000
b10001010 -
1$
#1390000
b10001011 -
1#
0$
#1400000
b10001100 -
1$
#1410000
b10001101 -
1,
0#
0$
#1420000
b10001110 -
1$
#1430000
b10001111 -
1#
0$
#1440000
b10010000 -
1$
#1450000
b10010001 -
1*
0+
0,
0#
0$
#1460000
b10010010 -
1$
#1470000
b10010011 -
1#
0$
#1480000
b10010100 -
1$
#1490000
b10010101 -
1,
0#
0$
#1500000
b10010110 -
1$
#1510000
b10010111 -
1#
0$
#1520000
b10011000 -
1$
#1530000
b10011001 -
1+
0,
0#
0$
#1540000
b10011010 -
1$
#1550000
b10011011 -
1#
0$
#1560000
b10011100 -
1$
#1570000
b10011101 -
1,
0#
0$
#1580000
b10011110 -
1$
#1590000
b10011111 -
1#
0$
#1600000
b10100000 -
1$
#1610000
b10100001 -
1)
0*
0+
0,
0#
0$
#1620000
b10100010 -
1$
#1630000
b10100011 -
1#
0$
#1640000
b10100100 -
1$
#1650000
b10100101 -
1,
0#
0$
#1660000
b10100110 -
1$
#1670000
b10100111 -
1#
0$
#1680000
b10101000 -
1$
#1690000
b10101001 -
1+
0,
0#
0$
#1700000
b10101010 -
1$
#1710000
b10101011 -
1#
0$
#1720000
b10101100 -
1$
#1730000
b10101101 -
1,
0#
0$
#1740000
b10101110 -
1$
#1750000
b10101111 -
1#
0$
#1760000
b10110000 -
1$
#1770000
b10110001 -
1*
0+
0,
0#
0$
#1780000
b10110010 -
1$
#1790000
b10110011 -
1#
0$
#1800000
b10110100 -
1$
#1810000
b10110101 -
1,
0#
0$
#1820000
b10110110 -
1$
#1830000
b10110111 -
1#
0$
#1840000
b10111000 -
1$
#1850000
b10111001 -
1+
0,
0#
0$
#1860000
b10111010 -
1$
#1870000
b10111011 -
1#
0$
#1880000
b10111100 -
1$
#1890000
b10111101 -
1,
0#
0$
#1900000
b10111110 -
1$
#1910000
b10111111 -
1#
0$
#1920000
b11000000 -
1$
#1930000
b11000001 -
1(
0)
0*
0+
0,
0#
0$
#1940000
b11000010 -
1$
#1950000
b11000011 -
1#
0$
#1960000
b11000100 -
1$
#1970000
b11000101 -
1,
0#
0$
#1980000
b11000110 -
1$
#1990000
b11000111 -
1#
0$
#2000000
b11001000 -
1$
#2010000
b11001001 -
1+
0,
0#
0$
#2020000
b11001010 -
1$
#2030000
b11001011 -
1#
0$
#2040000
b11001100 -
1$
#2050000
b11001101 -
1,
0#
0$
#2060000
b11001110 -
1$
#2070000
b11001111 -
1#
0$
#2080000
b11010000 -
1$
#2090000
b11010001 -
1*
0+
0,
0#
0$
#2100000
b11010010 -
1$
#2110000
b11010011 -
1#
0$
#2120000
b11010100 -
1$
#2130000
b11010101 -
1,
0#
0$
#2140000
b11010110 -
1$
#2150000
b11010111 -
1#
0$
#2160000
b11011000 -
1$
#2170000
b11011001 -
1+
0,
0#
0$
#2180000
b11011010 -
1$
#2190000
b11011011 -
1#
0$
#2200000
b11011100 -
1$
#2210000
b11011101 -
1,
0#
0$
#2220000
b11011110 -
1$
#2230000
b11011111 -
1#
0$
#2240000
b11100000 -
1$
#2250000
b11100001 -
1)
0*
0+
0,
0#
0$
#2260000
b11100010 -
1$
#2270000
b11100011 -
1#
0$
#2280000
b11100100 -
1$
#2290000
b11100101 -
1,
0#
0$
#2300000
b11100110 -
1$
#2310000
b11100111 -
1#
0$
#2320000
b11101000 -
1$
#2330000
b11101001 -
1+
0,
0#
0$
#2340000
b11101010 -
1$
#2350000
b11101011 -
1#
0$
#2360000
b11101100 -
1$
#2370000
b11101101 -
1,
0#
0$
#2380000
b11101110 -
1$
#2390000
b11101111 -
1#
0$
#2400000
b11110000 -
1$
#2410000
b11110001 -
1*
0+
0,
0#
0$
#2420000
b11110010 -
1$
#2430000
b11110011 -
1#
0$
#2440000
b11110100 -
1$
#2450000
b11110101 -
1,
0#
0$
#2460000
b11110110 -
1$
#2470000
b11110111 -
1#
0$
#2480000
b11111000 -
1$
#2490000
b11111001 -
1+
0,
0#
0$
#2500000
b11111010 -
1$
#2510000
b11111011 -
1#
0$
#2520000
b11111100 -
1$
#2530000
b11111101 -
1,
0#
0$
#2540000
b11111110 -
1$
#2550000
b11111111 -
1#
0$
#2560000
b100000000 -
1$
#2570000
03
02
14
b100000001 -
1&
0'
0(
0)
0*
0+
0,
0#
0$
#2580000
b100000010 -
1$
#2590000
b100000011 -
1#
0$
#2600000
b100000100 -
1$
#2610000
b100000101 -
1,
0#
0$
#2620000
b100000110 -
1$
#2630000
b100000111 -
1#
0$
#2640000
b100001000 -
1$
#2650000
b100001001 -
1+
0,
0#
0$
#2660000
b100001010 -
1$
#2670000
b100001011 -
1#
0$
#2680000
b100001100 -
1$
#2690000
b100001101 -
1,
0#
0$
#2700000
b100001110 -
1$
#2710000
b100001111 -
1#
0$
#2720000
b100010000 -
1$
#2730000
b100010001 -
1*
0+
0,
0#
0$
#2740000
b100010010 -
1$
#2750000
b100010011 -
1#
0$
#2760000
b100010100 -
1$
#2770000
b100010101 -
1,
0#
0$
#2780000
b100010110 -
1$
#2790000
b100010111 -
1#
0$
#2800000
b100011000 -
1$
#2810000
b100011001 -
1+
0,
0#
0$
#2820000
b100011010 -
1$
#2830000
b100011011 -
1#
0$
#2840000
b100011100 -
1$
#2850000
b100011101 -
1,
0#
0$
#2860000
b100011110 -
1$
#2870000
b100011111 -
1#
0$
#2880000
b100100000 -
1$
#2890000
b100100001 -
1)
0*
0+
0,
0#
0$
#2900000
b100100010 -
1$
#2910000
b100100011 -
1#
0$
#2920000
b100100100 -
1$
#2930000
b100100101 -
1,
0#
0$
#2940000
b100100110 -
1$
#2950000
b100100111 -
1#
0$
#2960000
b100101000 -
1$
#2970000
b100101001 -
1+
0,
0#
0$
#2980000
b100101010 -
1$
#2990000
b100101011 -
1#
0$
#3000000
b100101100 -
1$
#3010000
b100101101 -
1,
0#
0$
#3020000
b100101110 -
1$
#3030000
b100101111 -
1#
0$
#3040000
b100110000 -
1$
#3050000
b100110001 -
1*
0+
0,
0#
0$
#3060000
b100110010 -
1$
#3070000
b100110011 -
1#
0$
#3080000
b100110100 -
1$
#3090000
b100110101 -
1,
0#
0$
#3100000
b100110110 -
1$
#3110000
b100110111 -
1#
0$
#3120000
b100111000 -
1$
#3130000
b100111001 -
1+
0,
0#
0$
#3140000
b100111010 -
1$
#3150000
b100111011 -
1#
0$
#3160000
b100111100 -
1$
#3170000
b100111101 -
1,
0#
0$
#3180000
b100111110 -
1$
#3190000
b100111111 -
1#
0$
#3200000
b101000000 -
1$
#3210000
b101000001 -
1(
0)
0*
0+
0,
0#
0$
#3220000
b101000010 -
1$
#3230000
b101000011 -
1#
0$
#3240000
b101000100 -
1$
#3250000
b101000101 -
1,
0#
0$
#3260000
b101000110 -
1$
#3270000
b101000111 -
1#
0$
#3280000
b101001000 -
1$
#3290000
b101001001 -
1+
0,
0#
0$
#3300000
b101001010 -
1$
#3310000
b101001011 -
1#
0$
#3320000
b101001100 -
1$
#3330000
b101001101 -
1,
0#
0$
#3340000
b101001110 -
1$
#3350000
b101001111 -
1#
0$
#3360000
b101010000 -
1$
#3370000
b101010001 -
1*
0+
0,
0#
0$
#3380000
b101010010 -
1$
#3390000
b101010011 -
1#
0$
#3400000
b101010100 -
1$
#3410000
b101010101 -
1,
0#
0$
#3420000
b101010110 -
1$
#3430000
b101010111 -
1#
0$
#3440000
b101011000 -
1$
#3450000
b101011001 -
1+
0,
0#
0$
#3460000
b101011010 -
1$
#3470000
b101011011 -
1#
0$
#3480000
b101011100 -
1$
#3490000
b101011101 -
1,
0#
0$
#3500000
b101011110 -
1$
#3510000
b101011111 -
1#
0$
#3520000
b101100000 -
1$
#3530000
b101100001 -
1)
0*
0+
0,
0#
0$
#3540000
b101100010 -
1$
#3550000
b101100011 -
1#
0$
#3560000
b101100100 -
1$
#3570000
b101100101 -
1,
0#
0$
#3580000
b101100110 -
1$
#3590000
b101100111 -
1#
0$
#3600000
b101101000 -
1$
#3610000
b101101001 -
1+
0,
0#
0$
#3620000
b101101010 -
1$
#3630000
b101101011 -
1#
0$
#3640000
b101101100 -
1$
#3650000
b101101101 -
1,
0#
0$
#3660000
b101101110 -
1$
#3670000
b101101111 -
1#
0$
#3680000
b101110000 -
1$
#3690000
b101110001 -
1*
0+
0,
0#
0$
#3700000
b101110010 -
1$
#3710000
b101110011 -
1#
0$
#3720000
b101110100 -
1$
#3730000
b101110101 -
1,
0#
0$
#3740000
b101110110 -
1$
#3750000
b101110111 -
1#
0$
#3760000
b101111000 -
1$
#3770000
b101111001 -
1+
0,
0#
0$
#3780000
b101111010 -
1$
#3790000
b101111011 -
1#
0$
#3800000
b101111100 -
1$
#3810000
b101111101 -
1,
0#
0$
#3820000
b101111110 -
1$
#3830000
b101111111 -
1#
0$
#3840000
b110000000 -
1$
#3850000
b110000001 -
1'
0(
0)
0*
0+
0,
0#
0$
#3860000
b110000010 -
1$
#3870000
b110000011 -
1#
0$
#3880000
b110000100 -
1$
#3890000
b110000101 -
1,
0#
0$
#3900000
b110000110 -
1$
#3910000
b110000111 -
1#
0$
#3920000
b110001000 -
1$
#3930000
b110001001 -
1+
0,
0#
0$
#3940000
b110001010 -
1$
#3950000
b110001011 -
1#
0$
#3960000
b110001100 -
1$
#3970000
b110001101 -
1,
0#
0$
#3980000
b110001110 -
1$
#3990000
b110001111 -
1#
0$
#4000000
b110010000 -
1$
#4010000
b110010001 -
1*
0+
0,
0#
0$
#4020000
b110010010 -
1$
#4030000
b110010011 -
1#
0$
#4040000
b110010100 -
1$
#4050000
b110010101 -
1,
0#
0$
#4060000
b110010110 -
1$
#4070000
b110010111 -
1#
0$
#4080000
b110011000 -
1$
#4090000
b110011001 -
1+
0,
0#
0$
#4100000
b110011010 -
1$
#4110000
b110011011 -
1#
0$
#4120000
b110011100 -
1$
#4130000
b110011101 -
1,
0#
0$
#4140000
b110011110 -
1$
#4150000
b110011111 -
1#
0$
#4160000
b110100000 -
1$
#4170000
b110100001 -
1)
0*
0+
0,
0#
0$
#4180000
b110100010 -
1$
#4190000
b110100011 -
1#
0$
#4200000
b110100100 -
1$
#4210000
b110100101 -
1,
0#
0$
#4220000
b110100110 -
1$
#4230000
b110100111 -
1#
0$
#4240000
b110101000 -
1$
#4250000
b110101001 -
1+
0,
0#
0$
#4260000
b110101010 -
1$
#4270000
b110101011 -
1#
0$
#4280000
b110101100 -
1$
#4290000
b110101101 -
1,
0#
0$
#4300000
b110101110 -
1$
#4310000
b110101111 -
1#
0$
#4320000
b110110000 -
1$
#4330000
b110110001 -
1*
0+
0,
0#
0$
#4340000
b110110010 -
1$
#4350000
b110110011 -
1#
0$
#4360000
b110110100 -
1$
#4370000
b110110101 -
1,
0#
0$
#4380000
b110110110 -
1$
#4390000
b110110111 -
1#
0$
#4400000
b110111000 -
1$
#4410000
b110111001 -
1+
0,
0#
0$
#4420000
b110111010 -
1$
#4430000
b110111011 -
1#
0$
#4440000
b110111100 -
1$
#4450000
b110111101 -
1,
0#
0$
#4460000
b110111110 -
1$
#4470000
b110111111 -
1#
0$
#4480000
b111000000 -
1$
#4490000
b111000001 -
1(
0)
0*
0+
0,
0#
0$
#4500000
b111000010 -
1$
#4510000
b111000011 -
1#
0$
#4520000
b111000100 -
1$
#4530000
b111000101 -
1,
0#
0$
#4540000
b111000110 -
1$
#4550000
b111000111 -
1#
0$
#4560000
b111001000 -
1$
#4570000
b111001001 -
1+
0,
0#
0$
#4580000
b111001010 -
1$
#4590000
b111001011 -
1#
0$
#4600000
b111001100 -
1$
#4610000
b111001101 -
1,
0#
0$
#4620000
b111001110 -
1$
#4630000
b111001111 -
1#
0$
#4640000
b111010000 -
1$
#4650000
b111010001 -
1*
0+
0,
0#
0$
#4660000
b111010010 -
1$
#4670000
b111010011 -
1#
0$
#4680000
b111010100 -
1$
#4690000
b111010101 -
1,
0#
0$
#4700000
b111010110 -
1$
#4710000
b111010111 -
1#
0$
#4720000
b111011000 -
1$
#4730000
b111011001 -
1+
0,
0#
0$
#4740000
b111011010 -
1$
#4750000
b111011011 -
1#
0$
#4760000
b111011100 -
1$
#4770000
b111011101 -
1,
0#
0$
#4780000
b111011110 -
1$
#4790000
b111011111 -
1#
0$
#4800000
b111100000 -
1$
#4810000
b111100001 -
1)
0*
0+
0,
0#
0$
#4820000
b111100010 -
1$
#4830000
b111100011 -
1#
0$
#4840000
b111100100 -
1$
#4850000
b111100101 -
1,
0#
0$
#4860000
b111100110 -
1$
#4870000
b111100111 -
1#
0$
#4880000
b111101000 -
1$
#4890000
b111101001 -
1+
0,
0#
0$
#4900000
b111101010 -
1$
#4910000
b111101011 -
1#
0$
#4920000
b111101100 -
1$
#4930000
b111101101 -
1,
0#
0$
#4940000
b111101110 -
1$
#4950000
b111101111 -
1#
0$
#4960000
b111110000 -
1$
#4970000
b111110001 -
1*
0+
0,
0#
0$
#4980000
b111110010 -
1$
#4990000
b111110011 -
1#
0$
#5000000
b111110100 -
1$
#5010000
b111110101 -
1,
0#
0$
#5020000
b111110110 -
1$
#5030000
b111110111 -
1#
0$
#5040000
b111111000 -
1$
#5050000
b111111001 -
1+
0,
0#
0$
#5060000
b111111010 -
1$
#5070000
b111111011 -
1#
0$
#5080000
b111111100 -
1$
#5090000
b111111101 -
1,
0#
0$
#5100000
b111111110 -
1$
#5110000
b111111111 -
1#
0$
#5120000
b1000000000 -
1$
#5130000
01
15
12
04
b1000000001 -
1%
0&
0'
0(
0)
0*
0+
0,
0#
0$
#5140000
b1000000010 -
1$
#5150000
b1000000011 -
1#
0$
#5160000
b1000000100 -
1$
#5170000
b1000000101 -
1,
0#
0$
#5180000
b1000000110 -
1$
#5190000
b1000000111 -
1#
0$
#5200000
b1000001000 -
1$
#5210000
b1000001001 -
1+
0,
0#
0$
#5220000
b1000001010 -
1$
#5230000
b1000001011 -
1#
0$
#5240000
b1000001100 -
1$
#5250000
b1000001101 -
1,
0#
0$
#5260000
b1000001110 -
1$
#5270000
b1000001111 -
1#
0$
#5280000
b1000010000 -
1$
#5290000
b1000010001 -
1*
0+
0,
0#
0$
#5300000
b1000010010 -
1$
#5310000
b1000010011 -
1#
0$
#5320000
b1000010100 -
1$
#5330000
b1000010101 -
1,
0#
0$
#5340000
b1000010110 -
1$
#5350000
b1000010111 -
1#
0$
#5360000
b1000011000 -
1$
#5370000
b1000011001 -
1+
0,
0#
0$
#5380000
b1000011010 -
1$
#5390000
b1000011011 -
1#
0$
#5400000
b1000011100 -
1$
#5410000
b1000011101 -
1,
0#
0$
#5420000
b1000011110 -
1$
#5430000
b1000011111 -
1#
0$
#5440000
b1000100000 -
1$
#5450000
b1000100001 -
1)
0*
0+
0,
0#
0$
#5460000
b1000100010 -
1$
#5470000
b1000100011 -
1#
0$
#5480000
b1000100100 -
1$
#5490000
b1000100101 -
1,
0#
0$
#5500000
b1000100110 -
1$
#5510000
b1000100111 -
1#
0$
#5520000
b1000101000 -
1$
#5530000
b1000101001 -
1+
0,
0#
0$
#5540000
b1000101010 -
1$
#5550000
b1000101011 -
1#
0$
#5560000
b1000101100 -
1$
#5570000
b1000101101 -
1,
0#
0$
#5580000
b1000101110 -
1$
#5590000
b1000101111 -
1#
0$
#5600000
b1000110000 -
1$
#5610000
b1000110001 -
1*
0+
0,
0#
0$
#5620000
b1000110010 -
1$
#5630000
b1000110011 -
1#
0$
#5640000
b1000110100 -
1$
#5650000
b1000110101 -
1,
0#
0$
#5660000
b1000110110 -
1$
#5670000
b1000110111 -
1#
0$
#5680000
b1000111000 -
1$
#5690000
b1000111001 -
1+
0,
0#
0$
#5700000
b1000111010 -
1$
#5710000
b1000111011 -
1#
0$
#5720000
b1000111100 -
1$
#5730000
b1000111101 -
1,
0#
0$
#5740000
b1000111110 -
1$
#5750000
b1000111111 -
1#
0$
#5760000
b1001000000 -
1$
#5770000
b1001000001 -
1(
0)
0*
0+
0,
0#
0$
#5780000
b1001000010 -
1$
#5790000
b1001000011 -
1#
0$
#5800000
b1001000100 -
1$
#5810000
b1001000101 -
1,
0#
0$
#5820000
b1001000110 -
1$
#5830000
b1001000111 -
1#
0$
#5840000
b1001001000 -
1$
#5850000
b1001001001 -
1+
0,
0#
0$
#5860000
b1001001010 -
1$
#5870000
b1001001011 -
1#
0$
#5880000
b1001001100 -
1$
#5890000
b1001001101 -
1,
0#
0$
#5900000
b1001001110 -
1$
#5910000
b1001001111 -
1#
0$
#5920000
b1001010000 -
1$
#5930000
b1001010001 -
1*
0+
0,
0#
0$
#5940000
b1001010010 -
1$
#5950000
b1001010011 -
1#
0$
#5960000
b1001010100 -
1$
#5970000
b1001010101 -
1,
0#
0$
#5980000
b1001010110 -
1$
#5990000
b1001010111 -
1#
0$
#6000000
b1001011000 -
1$
#6010000
b1001011001 -
1+
0,
0#
0$
#6020000
b1001011010 -
1$
#6030000
b1001011011 -
1#
0$
#6040000
b1001011100 -
1$
#6050000
b1001011101 -
1,
0#
0$
#6060000
b1001011110 -
1$
#6070000
b1001011111 -
1#
0$
#6080000
b1001100000 -
1$
#6090000
b1001100001 -
1)
0*
0+
0,
0#
0$
#6100000
b1001100010 -
1$
#6110000
b1001100011 -
1#
0$
#6120000
b1001100100 -
1$
#6130000
b1001100101 -
1,
0#
0$
#6140000
b1001100110 -
1$
#6150000
b1001100111 -
1#
0$
#6160000
b1001101000 -
1$
#6170000
b1001101001 -
1+
0,
0#
0$
#6180000
b1001101010 -
1$
#6190000
b1001101011 -
1#
0$
#6200000
b1001101100 -
1$
#6210000
b1001101101 -
1,
0#
0$
#6220000
b1001101110 -
1$
#6230000
b1001101111 -
1#
0$
#6240000
b1001110000 -
1$
#6250000
b1001110001 -
1*
0+
0,
0#
0$
#6260000
b1001110010 -
1$
#6270000
b1001110011 -
1#
0$
#6280000
b1001110100 -
1$
#6290000
b1001110101 -
1,
0#
0$
#6300000
b1001110110 -
1$
#6310000
b1001110111 -
1#
0$
#6320000
b1001111000 -
1$
#6330000
b1001111001 -
1+
0,
0#
0$
#6340000
b1001111010 -
1$
#6350000
b1001111011 -
1#
0$
#6360000
b1001111100 -
1$
#6370000
b1001111101 -
1,
0#
0$
#6380000
b1001111110 -
1$
#6390000
b1001111111 -
1#
0$
#6400000
b1010000000 -
1$
#6410000
b1010000001 -
1'
0(
0)
0*
0+
0,
0#
0$
#6420000
b1010000010 -
1$
#6430000
b1010000011 -
1#
0$
#6440000
b1010000100 -
1$
#6450000
b1010000101 -
1,
0#
0$
#6460000
b1010000110 -
1$
#6470000
b1010000111 -
1#
0$
#6480000
b1010001000 -
1$
#6490000
b1010001001 -
1+
0,
0#
0$
#6500000
b1010001010 -
1$
#6510000
b1010001011 -
1#
0$
#6520000
b1010001100 -
1$
#6530000
b1010001101 -
1,
0#
0$
#6540000
b1010001110 -
1$
#6550000
b1010001111 -
1#
0$
#6560000
b1010010000 -
1$
#6570000
b1010010001 -
1*
0+
0,
0#
0$
#6580000
b1010010010 -
1$
#6590000
b1010010011 -
1#
0$
#6600000
b1010010100 -
1$
#6610000
b1010010101 -
1,
0#
0$
#6620000
b1010010110 -
1$
#6630000
b1010010111 -
1#
0$
#6640000
b1010011000 -
1$
#6650000
b1010011001 -
1+
0,
0#
0$
#6660000
b1010011010 -
1$
#6670000
b1010011011 -
1#
0$
#6680000
b1010011100 -
1$
#6690000
b1010011101 -
1,
0#
0$
#6700000
b1010011110 -
1$
#6710000
b1010011111 -
1#
0$
#6720000
b1010100000 -
1$
#6730000
b1010100001 -
1)
0*
0+
0,
0#
0$
#6740000
b1010100010 -
1$
#6750000
b1010100011 -
1#
0$
#6760000
b1010100100 -
1$
#6770000
b1010100101 -
1,
0#
0$
#6780000
b1010100110 -
1$
#6790000
b1010100111 -
1#
0$
#6800000
b1010101000 -
1$
#6810000
b1010101001 -
1+
0,
0#
0$
#6820000
b1010101010 -
1$
#6830000
b1010101011 -
1#
0$
#6840000
b1010101100 -
1$
#6850000
b1010101101 -
1,
0#
0$
#6860000
b1010101110 -
1$
#6870000
b1010101111 -
1#
0$
#6880000
b1010110000 -
1$
#6890000
b1010110001 -
1*
0+
0,
0#
0$
#6900000
b1010110010 -
1$
#6910000
b1010110011 -
1#
0$
#6920000
b1010110100 -
1$
#6930000
b1010110101 -
1,
0#
0$
#6940000
b1010110110 -
1$
#6950000
b1010110111 -
1#
0$
#6960000
b1010111000 -
1$
#6970000
b1010111001 -
1+
0,
0#
0$
#6980000
b1010111010 -
1$
#6990000
b1010111011 -
1#
0$
#7000000
b1010111100 -
1$
#7010000
b1010111101 -
1,
0#
0$
#7020000
b1010111110 -
1$
#7030000
b1010111111 -
1#
0$
#7040000
b1011000000 -
1$
#7050000
b1011000001 -
1(
0)
0*
0+
0,
0#
0$
#7060000
b1011000010 -
1$
#7070000
b1011000011 -
1#
0$
#7080000
b1011000100 -
1$
#7090000
b1011000101 -
1,
0#
0$
#7100000
b1011000110 -
1$
#7110000
b1011000111 -
1#
0$
#7120000
b1011001000 -
1$
#7130000
b1011001001 -
1+
0,
0#
0$
#7140000
b1011001010 -
1$
#7150000
b1011001011 -
1#
0$
#7160000
b1011001100 -
1$
#7170000
b1011001101 -
1,
0#
0$
#7180000
b1011001110 -
1$
#7190000
b1011001111 -
1#
0$
#7200000
b1011010000 -
1$
#7210000
b1011010001 -
1*
0+
0,
0#
0$
#7220000
b1011010010 -
1$
#7230000
b1011010011 -
1#
0$
#7240000
b1011010100 -
1$
#7250000
b1011010101 -
1,
0#
0$
#7260000
b1011010110 -
1$
#7270000
b1011010111 -
1#
0$
#7280000
b1011011000 -
1$
#7290000
b1011011001 -
1+
0,
0#
0$
#7300000
b1011011010 -
1$
#7310000
b1011011011 -
1#
0$
#7320000
b1011011100 -
1$
#7330000
b1011011101 -
1,
0#
0$
#7340000
b1011011110 -
1$
#7350000
b1011011111 -
1#
0$
#7360000
b1011100000 -
1$
#7370000
b1011100001 -
1)
0*
0+
0,
0#
0$
#7380000
b1011100010 -
1$
#7390000
b1011100011 -
1#
0$
#7400000
b1011100100 -
1$
#7410000
b1011100101 -
1,
0#
0$
#7420000
b1011100110 -
1$
#7430000
b1011100111 -
1#
0$
#7440000
b1011101000 -
1$
